setup.py
git/__init__.py
git/cmd.py
git/compat.py
git/config.py
git/db.py
git/diff.py
git/exc.py
git/remote.py
git/util.py
git/index/__init__.py
git/index/base.py
git/index/fun.py
git/index/typ.py
git/index/util.py
git/objects/__init__.py
git/objects/base.py
git/objects/blob.py
git/objects/commit.py
git/objects/fun.py
git/objects/tag.py
git/objects/tree.py
git/objects/util.py
git/objects/submodule/__init__.py
git/objects/submodule/base.py
git/objects/submodule/root.py
git/objects/submodule/util.py
git/refs/__init__.py
git/refs/head.py
git/refs/log.py
git/refs/reference.py
git/refs/remote.py
git/refs/symbolic.py
git/refs/tag.py
git/repo/__init__.py
git/repo/base.py
git/repo/fun.py
gitdb/__init__.py
gitdb/base.py
gitdb/const.py
gitdb/exc.py
gitdb/fun.py
gitdb/pack.py
gitdb/stream.py
gitdb/typ.py
gitdb/util.py
gitdb/db/__init__.py
gitdb/db/base.py
gitdb/db/git.py
gitdb/db/loose.py
gitdb/db/mem.py
gitdb/db/pack.py
gitdb/db/ref.py
gitdb/utils/__init__.py
gitdb/utils/compat.py
gitdb/utils/encoding.py
yoctools/__init__.py
yoctools/builder.py
yoctools/cmd.py
yoctools/command.py
yoctools/component.py
yoctools/gitproject.py
yoctools/log.py
yoctools/make.py
yoctools/occ.py
yoctools/package.py
yoctools/progress.py
yoctools/repo.py
yoctools/solution.py
yoctools/toolchain.py
yoctools/tools.py
yoctools/yoc.py
yoctools/site_tools/__init__.py
yoctools/site_tools/objcopy.py
yoctools/site_tools/objdump.py
yoctools/site_tools/product.py
yoctools/subcmds/__init__.py
yoctools/subcmds/addkey.py
yoctools/subcmds/branch.py
yoctools/subcmds/cdk.py
yoctools/subcmds/checkout.py
yoctools/subcmds/convert.py
yoctools/subcmds/export.py
yoctools/subcmds/format.py
yoctools/subcmds/help.py
yoctools/subcmds/init.py
yoctools/subcmds/install.py
yoctools/subcmds/list.py
yoctools/subcmds/rename.py
yoctools/subcmds/sdk.py
yoctools/subcmds/search.py
yoctools/subcmds/show.py
yoctools/subcmds/sync.py
yoctools/subcmds/toolchain.py
yoctools/subcmds/uninstall.py
yoctools/subcmds/upload.py
yoctools_t1.egg-info/PKG-INFO
yoctools_t1.egg-info/SOURCES.txt
yoctools_t1.egg-info/dependency_links.txt
yoctools_t1.egg-info/entry_points.txt
yoctools_t1.egg-info/requires.txt
yoctools_t1.egg-info/top_level.txt